typing_test/__init__.py
typing_test/__main__.py
typing_test/typing_test.py
typing_test/data/vocab
typing_test-0.1.0.data/scripts/tt
typing_test-0.1.0.dist-info/LICENSE
typing_test-0.1.0.dist-info/METADATA
typing_test-0.1.0.dist-info/WHEEL
typing_test-0.1.0.dist-info/top_level.txt
typing_test-0.1.0.dist-info/RECORD
