Metadata-Version: 2.1
Name: typing-test
Version: 0.1.0
Summary: Typing test in the terminal similar to 10fastfingers
Home-page: http://www.github.com/ecly/typing_test
Author: Emil Lynegaard
Author-email: ecly@mailbox.org
License: MIT
Keywords: typing,typing test,10fastfingers,cmd,terminal,game,ncurses,curses
Platform: UNKNOWN
